exsnap/__init__.py
exsnap/__main__.py
exsnap-0.0.1.dist-info/LICENSE
exsnap-0.0.1.dist-info/METADATA
exsnap-0.0.1.dist-info/WHEEL
exsnap-0.0.1.dist-info/entry_points.txt
exsnap-0.0.1.dist-info/top_level.txt
exsnap-0.0.1.dist-info/RECORD
