Metadata-Version: 2.1
Name: exsnap
Version: 0.0.1
Summary: Automate the downloading of Snapchat memories
Home-page: https://github.com/yttrian/exsnap
Author: Ian Moore
Author-email: exsnap@yttr.org
License: UNKNOWN
Platform: UNKNOWN
Classifier: Programming Language :: Python :: 3
Classifier: License :: OSI Approved :: MIT License
Classifier: Operating System :: OS Independent
Requires-Python: >=3.6
Requires-Dist: click
Requires-Dist: aiohttp
Requires-Dist: aiofiles
Requires-Dist: alive-progress
